community_mailbot/__init__.py
community_mailbot/contentpipe.py
community_mailbot/discourse.py
community_mailbot/scripts/__init__.py
community_mailbot/scripts/discourse_categories.py
community_mailbot/scripts/forward_discourse.py
community_mailbot-0.1.1.dist-info/DESCRIPTION.rst
community_mailbot-0.1.1.dist-info/METADATA
community_mailbot-0.1.1.dist-info/RECORD
community_mailbot-0.1.1.dist-info/WHEEL
community_mailbot-0.1.1.dist-info/entry_points.txt
community_mailbot-0.1.1.dist-info/metadata.json
community_mailbot-0.1.1.dist-info/top_level.txt
