Metadata-Version: 2.0
Name: community-mailbot
Version: 0.1.1
Summary: Friendly mail forwarding bot for community.lsst.org
Home-page: https://github.com/lsst-sqre/community_mailbot
Author: Jonathan Sick
Author-email: jsick@lsst.org
License: MIT
Keywords: astronomy discourse email
Platform: UNKNOWN
Classifier: Development Status :: 4 - Beta
Classifier: License :: OSI Approved :: GNU General Public License v3 (GPLv3)
Classifier: Programming Language :: Python :: 3.5
Requires-Dist: beautifulsoup4
Requires-Dist: mandrill
Requires-Dist: requests
